PYRipGREP/LICENSE
PYRipGREP/README.MD
PYRipGREP/__init__.py
PYRipGREP/requirements.txt
PYRipGREP/thirdparty.json
PYRipGREP-0.21.dist-info/LICENSE.rst
PYRipGREP-0.21.dist-info/METADATA
PYRipGREP-0.21.dist-info/WHEEL
PYRipGREP-0.21.dist-info/top_level.txt
PYRipGREP-0.21.dist-info/RECORD
