Metadata-Version: 2.1
Name: PYRipGREP
Version: 0.21
Summary: Use insanely fast regex engine RIPGREP as a python module! Search results are captured and converted to dict/numpy/pandas/generator
Home-page: https://github.com/hansalemaos/PYRipGREP
Author: Johannes Fischer
Author-email: <aulasparticularesdealemaosp@gmail.com>
License: MIT
Keywords: regex,ripgrep,grep,re,regular,expressions
Classifier: Development Status :: 4 - Beta
Classifier: Programming Language :: Python :: 3 :: Only
Classifier: Programming Language :: Python :: 3.9
Classifier: Topic :: Scientific/Engineering :: Visualization
Classifier: Topic :: Software Development :: Libraries :: Python Modules
Classifier: Topic :: Text Editors :: Text Processing
Classifier: Topic :: Text Processing :: General
Classifier: Topic :: Text Processing :: Indexing
Classifier: Topic :: Text Processing :: Filters
Classifier: Topic :: Utilities
License-File: LICENSE.rst
Requires-Dist: flatten-everything
Requires-Dist: numpy
Requires-Dist: pandas
Requires-Dist: regex
Requires-Dist: ujson
